Metadata-Version: 2.1
Name: pyco-template
Version: 0.0.1
Summary: support json template for python developers
Home-page: http://github.com/dodoru/pyco-template
Author: dodoru
Author-email: dodoru@foxmail.com
Maintainer: dodoru
Maintainer-email: dodoru@foxmail.com
License: GNU LGPLv3
Keywords: Python json template format render
Platform: any
Classifier: Development Status :: 4 - Beta
Classifier: Intended Audience :: Developers
Classifier: Topic :: Software Development :: Build Tools
Classifier: Topic :: Software Development :: Libraries :: Python Modules
Classifier: Topic :: Internet :: WWW/HTTP :: Dynamic Content
Classifier: License :: OSI Approved :: GNU General Public License v3 (GPLv3)
Classifier: Programming Language :: Python
Classifier: Programming Language :: Python :: 3
Classifier: Programming Language :: Python :: 3.5
Classifier: Programming Language :: Python :: 3.6
Classifier: Programming Language :: Python :: 3.7
Classifier: Programming Language :: Python :: 3.8
Classifier: Programming Language :: Python :: 3.9
